Metadata-Version: 2.1
Name: py-file-conf-gui
Version: 0.2.0
Summary: Web GUI for pyfileconf
Home-page: https://github.com/nickderobertis/py-file-conf-gui
Author: Nick DeRobertis
Author-email: whoopnip@gmail.com
License: MIT
Project-URL: Code, https://github.com/nickderobertis/py-file-conf-gui
Project-URL: Documentation, https://nickderobertis.github.io/py-file-conf-gui
Platform: UNKNOWN
Classifier: Development Status :: 3 - Alpha
Classifier: Intended Audience :: Developers
Classifier: Programming Language :: Python :: 3.6
Classifier: Programming Language :: Python :: 3.7
Requires-Dist: dash
Requires-Dist: pyfileconf
Requires-Dist: dash-keyed-file-browser
